jupyterlab_ghostty/__init__.py
jupyterlab_ghostty/_version.py
jupyterlab_ghostty/labextension/build_log.json
jupyterlab_ghostty/labextension/package.json
jupyterlab_ghostty/labextension/schemas/jupyterlab-ghostty/package.json.orig
jupyterlab_ghostty/labextension/schemas/jupyterlab-ghostty/plugin.json
jupyterlab_ghostty/labextension/static/lib_index_js.9b90d34f702d353d745e.js
jupyterlab_ghostty/labextension/static/lib_index_js.9b90d34f702d353d745e.js.map
jupyterlab_ghostty/labextension/static/node_modules_ghostty-web_dist___vite-browser-external-2447137e_js.3b1fd27b1e643472837a.js
jupyterlab_ghostty/labextension/static/node_modules_ghostty-web_dist___vite-browser-external-2447137e_js.3b1fd27b1e643472837a.js.map
jupyterlab_ghostty/labextension/static/remoteEntry.7ac8af2e5edc6762f4f8.js
jupyterlab_ghostty/labextension/static/remoteEntry.7ac8af2e5edc6762f4f8.js.map
jupyterlab_ghostty/labextension/static/style.js
jupyterlab_ghostty/labextension/static/style_index_js.1531fb0861531fc42925.js
jupyterlab_ghostty/labextension/static/style_index_js.1531fb0861531fc42925.js.map
jupyterlab_ghostty/labextension/static/vendors-node_modules_ghostty-web_dist_ghostty-web_js.20f24d7479bf73bb9a15.js
jupyterlab_ghostty/labextension/static/vendors-node_modules_ghostty-web_dist_ghostty-web_js.20f24d7479bf73bb9a15.js.map
jupyterlab_ghostty-0.0.2.data/data/share/jupyter/labextensions/jupyterlab-ghostty/build_log.json
jupyterlab_ghostty-0.0.2.data/data/share/jupyter/labextensions/jupyterlab-ghostty/package.json
jupyterlab_ghostty-0.0.2.data/data/share/jupyter/labextensions/jupyterlab-ghostty/schemas/jupyterlab-ghostty/package.json.orig
jupyterlab_ghostty-0.0.2.data/data/share/jupyter/labextensions/jupyterlab-ghostty/schemas/jupyterlab-ghostty/plugin.json
jupyterlab_ghostty-0.0.2.data/data/share/jupyter/labextensions/jupyterlab-ghostty/static/lib_index_js.9b90d34f702d353d745e.js
jupyterlab_ghostty-0.0.2.dist-info/METADATA
jupyterlab_ghostty-0.0.2.dist-info/WHEEL
jupyterlab_ghostty-0.0.2.dist-info/licenses/LICENSE
jupyterlab_ghostty-0.0.2.dist-info/RECORD
