Metadata-Version: 2.4
Name: jupyterlab-ghostty
Version: 0.0.2
Dynamic: Keywords
Summary: JupyterLab terminal using ghostty-web (libghostty WASM)
Project-URL: Homepage, https://github.com/eexwhyzee/jupyterlab-ghostty
Project-URL: Repository, https://github.com/eexwhyzee/jupyterlab-ghostty.git
Author: JupyterLab Ghostty Contributors
License: BSD 3-Clause License
License-File: LICENSE
Classifier: Framework :: Jupyter
Classifier: Framework :: Jupyter :: JupyterLab
Classifier: Framework :: Jupyter :: JupyterLab :: 4
Classifier: Framework :: Jupyter :: JupyterLab :: Extensions
Classifier: Framework :: Jupyter :: JupyterLab :: Extensions :: Prebuilt
Classifier: License :: OSI Approved :: BSD License
Classifier: Programming Language :: Python
Classifier: Programming Language :: Python :: 3
Classifier: Programming Language :: Python :: 3.8
Classifier: Programming Language :: Python :: 3.9
Classifier: Programming Language :: Python :: 3.10
Classifier: Programming Language :: Python :: 3.11
Classifier: Programming Language :: Python :: 3.12
Requires-Python: >=3.8
